plenario_client/__init__.py
plenario_client/__version__.py
plenario_client/clients.py
plenario_client/errors.py
plenario_client/filters.py
plenario_client/responses.py
plenario_client-0.9.0.dist-info/LICENSE
plenario_client-0.9.0.dist-info/METADATA
plenario_client-0.9.0.dist-info/WHEEL
plenario_client-0.9.0.dist-info/top_level.txt
plenario_client-0.9.0.dist-info/RECORD
