Metadata-Version: 2.1
Name: plenario-client
Version: 0.9.0
Summary: The Official Python Client of the Array of Things API
Home-page: https://github.com/UrbanCCD-UChicago/plenario-client-py
Author: Vince Forgione
Author-email: vforgione@uchicago.edu
License: Apache-2.0
Platform: UNKNOWN
Classifier: Development Status :: 3 - Alpha
Classifier: Intended Audience :: Developers
Classifier: License :: OSI Approved :: Apache Software License
Classifier: Environment :: Console
Classifier: Environment :: Web Environment
Classifier: Intended Audience :: Developers
Classifier: Intended Audience :: Information Technology
Classifier: Intended Audience :: System Administrators
Classifier: Natural Language :: English
Classifier: Operating System :: OS Independent
Classifier: Programming Language :: Python :: 3.6
Classifier: Programming Language :: Python :: 3.7
Requires-Python: >=3.6
Requires-Dist: requests
